music_snapshot/__init__.py
music_snapshot/__main__.py
music_snapshot/cli.py
music_snapshot/config.py
music_snapshot/py.typed
music_snapshot/tracks.py
music_snapshot/utils.py
music_snapshot-0.1.0.dist-info/entry_points.txt
music_snapshot-0.1.0.dist-info/LICENSE
music_snapshot-0.1.0.dist-info/WHEEL
music_snapshot-0.1.0.dist-info/METADATA
music_snapshot-0.1.0.dist-info/RECORD
