Metadata-Version: 2.3
Name: music_snapshot
Version: 0.1.0
Summary: Save a snapshot of your day as a Spotify playlist.
Keywords: spotify,playlist,cli
Author-email: Paweł Adamczak <pawel.ad@gmail.com>
Requires-Python: >=3.10
Classifier: Development Status :: 4 - Beta
Classifier: Environment :: Console
Classifier: Intended Audience :: End Users/Desktop
Classifier: License :: OSI Approved :: Mozilla Public License 2.0 (MPL 2.0)
Classifier: Operating System :: OS Independent
Classifier: Programming Language :: Python
Classifier: Programming Language :: Python :: 3
Classifier: Programming Language :: Python :: 3.10
Classifier: Programming Language :: Python :: 3.11
Classifier: Programming Language :: Python :: 3.12
Classifier: Topic :: Utilities
Requires-Dist: click
Requires-Dist: click-default-group
Requires-Dist: pylast
Requires-Dist: questionary
Requires-Dist: rich
Requires-Dist: rich-click
Requires-Dist: spotipy
Requires-Dist: typing_extensions; python_version < '3.11'
Requires-Dist: music_snapshot[tests] ; extra == "dev"
Requires-Dist: black ; extra == "dev"
Requires-Dist: interrogate ; extra == "dev"
Requires-Dist: isort ; extra == "dev"
Requires-Dist: ruff ; extra == "dev"
Requires-Dist: mypy ; extra == "dev"
Requires-Dist: flit ; extra == "dev"
Requires-Dist: nox ; extra == "dev"
Requires-Dist: coverage[toml] ; extra == "tests"
Requires-Dist: pytest ; extra == "tests"
Project-URL: GitHub, https://github.com/pawelad/music_snapshot
Project-URL: Homepage, https://music_snapshot.pawelad.dev/
Project-URL: Issues, https://github.com/pawelad/music_snapshot/issues
Provides-Extra: dev
Provides-Extra: tests
